docstring_generator/__init__.py
docstring_generator/new_gen_docs.py
docstring_generator-0.3.4.dist-info/entry_points.txt
docstring_generator-0.3.4.dist-info/WHEEL
docstring_generator-0.3.4.dist-info/METADATA
docstring_generator-0.3.4.dist-info/RECORD
